Metadata-Version: 2.1
Name: ukrainian-profanity-filter
Version: 0.1
Summary: Censor ukrainian text
Home-page: UNKNOWN
Author: Mykhaylo Matviykiv
License: UNKNOWN
Platform: UNKNOWN
